modi/__init__.py
modi/__main__.py
modi/_exe_thrd.py
modi/about.py
modi/modi.py
modi/assets/firmware/esp32/bootloader.bin
modi/assets/firmware/esp32/esp32.bin
modi/assets/firmware/esp32/esp_version.txt
modi/assets/firmware/esp32/modi_ota_factory.bin
modi/assets/firmware/esp32/ota_data_initial.bin
modi/assets/firmware/esp32/partitions.bin
modi/assets/firmware/gd32/base_version.txt
modi/assets/firmware/gd32/network.bin
modi/assets/firmware/gd32/ultrasonic.bin
modi/assets/firmware/gd32/version.txt
modi/assets/firmware/stm32/base_version.txt
modi/assets/firmware/stm32/button.bin
modi/assets/firmware/stm32/dial.bin
modi/assets/firmware/stm32/display.bin
modi/assets/firmware/stm32/env.bin
modi/assets/firmware/stm32/gyro.bin
modi/assets/firmware/stm32/ir.bin
modi/assets/firmware/stm32/led.bin
modi/assets/firmware/stm32/mic.bin
modi/assets/firmware/stm32/motor.bin
modi/assets/firmware/stm32/network.bin
modi/assets/firmware/stm32/speaker.bin
modi/assets/firmware/stm32/ultrasonic.bin
modi/assets/firmware/stm32/version.txt
modi/module/__init__.py
modi/module/module.py
modi/module/input_module/__init__.py
modi/module/input_module/button.py
modi/module/input_module/dial.py
modi/module/input_module/env.py
modi/module/input_module/gyro.py
modi/module/input_module/input_module.py
modi/module/input_module/ir.py
modi/module/input_module/mic.py
modi/module/input_module/ultrasonic.py
modi/module/output_module/__init__.py
modi/module/output_module/display.py
modi/module/output_module/led.py
modi/module/output_module/motor.py
modi/module/output_module/output_module.py
modi/module/output_module/speaker.py
modi/module/setup_module/__init__.py
modi/module/setup_module/battery.py
modi/module/setup_module/network.py
modi/module/setup_module/setup_module.py
modi/task/__init__.py
modi/task/can_task.py
modi/task/conn_task.py
modi/task/exe_task.py
modi/task/ser_task.py
modi/task/soc_task.py
modi/task/vir_task.py
modi/task/ble_task/__init__.py
modi/task/ble_task/ble_task_mac.py
pymodi-1.2.0.dist-info/AUTHORS.md
pymodi-1.2.0.dist-info/LICENSE
pymodi-1.2.0.dist-info/METADATA
pymodi-1.2.0.dist-info/WHEEL
pymodi-1.2.0.dist-info/top_level.txt
pymodi-1.2.0.dist-info/RECORD
