Metadata-Version: 2.1
Name: pymodi
Version: 1.2.0
Summary: Python API for controlling modular electronics, MODI.
Home-page: https://github.com/LUXROBO/pymodi
Author: LUXROBO
Author-email: tech@luxrobo.com
License: MIT
Keywords: python,modi
Platform: UNKNOWN
Classifier: Natural Language :: English
Classifier: Intended Audience :: Developers
Classifier: Intended Audience :: Education
Classifier: Intended Audience :: Information Technology
Classifier: Intended Audience :: Science/Research
Classifier: Programming Language :: Python :: 3.6
Classifier: Programming Language :: Python :: 3.7
Classifier: Programming Language :: Python :: 3.8
Classifier: License :: OSI Approved :: MIT License
Classifier: Operating System :: OS Independent
Provides-Extra: dev
License-File: LICENSE
License-File: AUTHORS.md
